pythonbible_api/__init__.py
pythonbible_api/main.py
pythonbible_api-0.0.2.dist-info/LICENSE
pythonbible_api-0.0.2.dist-info/WHEEL
pythonbible_api-0.0.2.dist-info/METADATA
pythonbible_api-0.0.2.dist-info/RECORD
