Metadata-Version: 2.1
Name: pythonbible_api
Version: 0.0.2
Summary: pythonbible-api is an API wrapper for the pythonbible library using FastAPI.
Home-page: https://github.com/Fliturgy/pythonbible-api
Author: Fliturgy
Author-email: fliturgy@gmail.com
Requires-Python: >=3.7
Classifier: Intended Audience :: Information Technology
Classifier: Intended Audience :: Developers
Classifier: Operating System :: OS Independent
Classifier: Topic :: Software Development :: Libraries :: Python Modules
Classifier: Topic :: Software Development :: Libraries
Classifier: Topic :: Software Development
Classifier: Programming Language :: Python
Classifier: Programming Language :: Python :: 3
Classifier: Programming Language :: Python :: 3 :: Only
Classifier: Programming Language :: Python :: 3.7
Classifier: Programming Language :: Python :: 3.8
Classifier: Programming Language :: Python :: 3.9
Classifier: License :: OSI Approved :: MIT License
Requires-Dist: fastapi >=0.63.0
Requires-Dist: pythonbible ==0.3.1
Requires-Dist: bandit >=1.7.0 ; extra == "dev"
Requires-Dist: black >=20.8b1 ; extra == "dev"
Requires-Dist: mypy >=0.812 ; extra == "dev"
Requires-Dist: prospector >=1.3.1 ; extra == "dev"
Requires-Dist: uvicorn[standard] >=0.13.4 ; extra == "dev"
Requires-Dist: pytest >=6.2.2 ; extra == "test"
Requires-Dist: pytest-cov >=2.11.1 ; extra == "test"
Provides-Extra: all
Provides-Extra: dev
Provides-Extra: doc
Provides-Extra: test
